sphinx_togglebutton/__init__.py
sphinx_togglebutton/_static/togglebutton.css
sphinx_togglebutton/_static/togglebutton.js
sphinx_togglebutton-0.3.2.dist-info/LICENSE
sphinx_togglebutton-0.3.2.dist-info/METADATA
sphinx_togglebutton-0.3.2.dist-info/WHEEL
sphinx_togglebutton-0.3.2.dist-info/top_level.txt
sphinx_togglebutton-0.3.2.dist-info/RECORD
