Metadata-Version: 2.1
Name: sphinx-togglebutton
Version: 0.3.2
Summary: Toggle page content and collapse admonitions in Sphinx.
Home-page: https://github.com/executablebooks/sphinx-togglebutton
Author: Chris Holdgraf
Author-email: choldgraf@berkeley.edu
License: MIT License
Classifier: License :: OSI Approved :: MIT License
Provides-Extra: sphinx
License-File: LICENSE
